umapper/__init__.py
umapper/core.py
umapper-0.1.5.dist-info/licenses/LICENSE
umapper-0.1.5.dist-info/METADATA
umapper-0.1.5.dist-info/WHEEL
umapper-0.1.5.dist-info/top_level.txt
umapper-0.1.5.dist-info/RECORD
