Metadata-Version: 2.4
Name: umapper
Version: 0.1.5
Summary: Data mapping facilities
Author-email: Gustavo Venturini <gustavo.c.venturini@gmail.com>
License: MIT
Project-URL: Homepage, https://github.com/vottini/umapper
Classifier: Development Status :: 5 - Production/Stable
Classifier: Intended Audience :: Developers
Classifier: License :: OSI Approved :: MIT License
Classifier: Operating System :: OS Independent
Classifier: Programming Language :: Python :: 3 :: Only
Requires-Python: >=3.11
License-File: LICENSE
Requires-Dist: pyhumps==3.8.0
Dynamic: license-file
